abctoolwithpython/__init__.py
abctoolwithpython-0.0.1.dist-info/METADATA
abctoolwithpython-0.0.1.dist-info/WHEEL
abctoolwithpython-0.0.1.dist-info/top_level.txt
abctoolwithpython-0.0.1.dist-info/RECORD
