Metadata-Version: 2.1
Name: abctoolwithpython
Version: 0.0.1
Summary: A basic URL splitter tool
Author: Thejas hari
Author-email: <thejaskala308@gmail.com>
Keywords: python,url,url-splitter,endpoint splitter
Classifier: Development Status :: 1 - Planning
Classifier: Intended Audience :: Developers
Classifier: Programming Language :: Python :: 3
Classifier: Operating System :: Unix
Classifier: Operating System :: MacOS :: MacOS X
Classifier: Operating System :: Microsoft :: Windows
